<?xml version="1.0" encoding="utf-8"?>
<Atlas>
	<Texture filename="tea_inventoryitem.tex" />
	<Elements>
		<Element name="additive_dairy.tex" u1="0.626" u2="0.6865" v2="0.9365" v1="0.876" variant="" />
		<Element name="additive_nut.tex" u1="0.9385" u2="0.999" v2="0.874" v1="0.8135" variant="" />
		<Element name="additive_petals.tex" u1="0.4980703125" u2="0.5585703125" v2="0.749" v1="0.6885" variant="" />
		<Element name="additive_seed.tex" u1="0.8730703125" u2="0.9335703125" v2="0.8115" v1="0.751" variant="" />
		<Element name="barrel.tex" u1="0.811546875" u2="0.872046875" v2="0.624" v1="0.5635" variant="" />
		<Element name="brewery.tex" u1="0.6172109375" u2="0.6777109375" v2="0.1865" v1="0.126" variant="" />
		<Element name="desalinator.tex" u1="0.8086171875" u2="0.8691171875" v2="0.374" v1="0.3135" variant="" />
		<Element name="distillers.tex" u1="0.788109375" u2="0.848609375" v2="0.749" v1="0.6885" variant="" />
		<Element name="boilbook.tex" u1="0.876" u2="0.9365" v2="0.874" v1="0.8144765625" variant="" />
		<Element name="absinthe_bottle.tex" u1="0.001" u2="0.0615" v2="0.624" v1="0.5635" variant="" />
		<Element name="areuhi_bottle.tex" u1="0.251" u2="0.3115" v2="0.6865" v1="0.626" variant="" />
		<Element name="banana_juice_bottle.tex" u1="0.436546875" u2="0.497046875" v2="0.0615" v1="0.001" variant="" />
		<Element name="berries_juice_bottle.tex" u1="0.499046875" u2="0.559546875" v2="0.124" v1="0.0635" variant="" />
		<Element name="berry_brandy_bottle.tex" u1="0.4385" u2="0.499" v2="0.874" v1="0.8135" variant="" />
		<Element name="berry_gin_bottle.tex" u1="0.126" u2="0.1865" v2="0.5615" v1="0.501" variant="" />
		<Element name="blacktea_bottle.tex" u1="0.686546875" u2="0.747046875" v2="0.3115" v1="0.251" variant="" />
		<Element name="blacktea_iced_bottle.tex" u1="0.87209375" u2="0.93259375" v2="0.4472421875" v1="0.3867421875" variant="" />
		<Element name="butterbeer_bottle.tex" u1="0.9385" u2="0.999" v2="0.9365" v1="0.876" variant="" />
		<Element name="cactus_tea_bottle.tex" u1="0.80959375" u2="0.87009375" v2="0.4365" v1="0.376" variant="" />
		<Element name="cactusflower_tea_bottle.tex" u1="0.6230703125" u2="0.6835703125" v2="0.249" v1="0.1885" variant="" />
		<Element name="caffeinberry_juice_bottle.tex" u1="0.874046875" u2="0.934546875" v2="0.5068125" v1="0.4492421875" variant="" />
		<Element name="carrot_tea_bottle.tex" u1="0.436546875" u2="0.497046875" v2="0.124" v1="0.0635" variant="" />
		<Element name="cherry_bloom_madhu_bottle.tex" u1="0.1885" u2="0.249" v2="0.874" v1="0.8135" variant="" />
		<Element name="cherry_bloom_rum_bottle.tex" u1="0.124046875" u2="0.184546875" v2="0.8115" v1="0.751" variant="" />
		<Element name="cherry_doctor_cola_bottle.tex" u1="0.251" u2="0.3115" v2="0.9365" v1="0.876" variant="" />
		<Element name="cherry_honey_tea_bottle.tex" u1="0.3135" u2="0.374" v2="0.9365" v1="0.876" variant="" />
		<Element name="cherry_roseberries_tea_bottle.tex" u1="0.249046875" u2="0.309546875" v2="0.8115" v1="0.751" variant="" />
		<Element name="coconut_juice_bottle.tex" u1="0.126" u2="0.1865" v2="0.874" v1="0.8135" variant="" />
		<Element name="cola_bottle.tex" u1="0.557640625" u2="0.6152109375" v2="0.1865" v1="0.1289296875" variant="" />
		<Element name="colaquantum_bottle.tex" u1="0.7480703125" u2="0.8066171875" v2="0.3749765625" v1="0.3164296875" variant="" />
		<Element name="corn_beer_bottle.tex" u1="0.7480703125" u2="0.80759375" v2="0.4365" v1="0.3769765625" variant="" />
		<Element name="corn_whiskey_bottle.tex" u1="0.376" u2="0.4365" v2="0.5615" v1="0.501" variant="" />
		<Element name="disinfectant_bottle.tex" u1="0.501" u2="0.5615" v2="0.999" v1="0.9385" variant="" />
		<Element name="dragonjuice_bottle.tex" u1="0.5605703125" u2="0.6210703125" v2="0.249" v1="0.1885" variant="" />
		<Element name="empty_bottle.tex" u1="0.251" u2="0.3115" v2="0.5615" v1="0.501" variant="" />
		<Element name="fig_juice_bottle.tex" u1="0.6855703125" u2="0.7460703125" v2="0.374" v1="0.3135" variant="" />
		<Element name="fruitjuice_bottle.tex" u1="0.624046875" u2="0.684546875" v2="0.3115" v1="0.251" variant="" />
		<Element name="fruitsoda_bottle.tex" u1="0.501" u2="0.5585703125" v2="0.249" v1="0.1914296875" variant="" />
		<Element name="fuer_bottle.tex" u1="0.8066640625" u2="0.8671640625" v2="0.499" v1="0.4385" variant="" />
		<Element name="giant_blueberry_gin_bottle.tex" u1="0.4355703125" u2="0.4960703125" v2="0.749" v1="0.6885" variant="" />
		<Element name="giant_blueberry_wine_bottle.tex" u1="0.626" u2="0.6865" v2="0.624" v1="0.5635" variant="" />
		<Element name="glowberry_gin_bottle.tex" u1="0.126" u2="0.1865" v2="0.624" v1="0.5635" variant="" />
		<Element name="glowberryjuice_bottle.tex" u1="0.495140625" u2="0.555640625" v2="0.1865" v1="0.126" variant="" />
		<Element name="glowberrywine_bottle.tex" u1="0.376" u2="0.434546875" v2="0.0663828125" v1="0.0058828125" variant="" />
		<Element name="goopydrink_bottle.tex" u1="0.6230703125" u2="0.6835703125" v2="0.374" v1="0.3135" variant="" />
		<Element name="greentea_bottle.tex" u1="0.6855703125" u2="0.7460703125" v2="0.4365" v1="0.376" variant="" />
		<Element name="hibiscustea_bottle.tex" u1="0.561546875" u2="0.622046875" v2="0.3115" v1="0.251" variant="" />
		<Element name="hotruincolate_bottle.tex" u1="0.376" u2="0.4365" v2="0.6865" v1="0.626" variant="" />
		<Element name="kahlua_bottle.tex" u1="0.1230703125" u2="0.1835703125" v2="0.749" v1="0.6885" variant="" />
		<Element name="kumis_bottle.tex" u1="0.376" u2="0.4335703125" v2="0.1269296875" v1="0.0683828125" variant="" />
		<Element name="lemonlimesoda_bottle.tex" u1="0.5635" u2="0.6210703125" v2="0.374" v1="0.315453125" variant="" />
		<Element name="lotustea_bottle.tex" u1="0.7441640625" u2="0.8046640625" v2="0.499" v1="0.4385" variant="" />
		<Element name="lumpy_beer_bottle.tex" u1="0.5635" u2="0.624" v2="0.874" v1="0.8144765625" variant="" />
		<Element name="lumpy_tea_bottle.tex" u1="0.6885" u2="0.749" v2="0.6865" v1="0.626" variant="" />
		<Element name="lumpy_vodka_bottle.tex" u1="0.3135" u2="0.374" v2="0.6865" v1="0.626" variant="" />
		<Element name="lumpy_wine_bottle.tex" u1="0.6885" u2="0.749" v2="0.999" v1="0.9385" variant="" />
		<Element name="madhu_bottle.tex" u1="0.4355703125" u2="0.493140625" v2="0.1865" v1="0.127953125" variant="" />
		<Element name="mixflower_bottle.tex" u1="0.3105703125" u2="0.3710703125" v2="0.0615" v1="0.001" variant="" />
		<Element name="moon_blossom_tea_bottle.tex" u1="0.5635" u2="0.624" v2="0.5615" v1="0.501" variant="" />
		<Element name="mulled_bottle.tex" u1="0.4385" u2="0.499" v2="0.249" v1="0.1885" variant="" />
		<Element name="noblewine_bottle.tex" u1="0.376" u2="0.4335703125" v2="0.1865" v1="0.1289296875" variant="" />
		<Element name="nut_corn_whiskey_bottle.tex" u1="0.436546875" u2="0.497046875" v2="0.8115" v1="0.751" variant="" />
		<Element name="pale_beer_bottle.tex" u1="0.561546875" u2="0.622046875" v2="0.124" v1="0.0635" variant="" />
		<Element name="pale_whiskey_bottle.tex" u1="0.936546875" u2="0.997046875" v2="0.500953125" v1="0.440453125" variant="" />
		<Element name="petals_berry_brandy_bottle.tex" u1="0.001" u2="0.0615" v2="0.749" v1="0.6885" variant="" />
		<Element name="pineananas_juice_bottle.tex" u1="0.749046875" u2="0.809546875" v2="0.3115" v1="0.251" variant="" />
		<Element name="pineananassoda_bottle.tex" u1="0.001" u2="0.0615" v2="0.999" v1="0.9385" variant="" />
		<Element name="pomegranate_juice_bottle.tex" u1="0.3135" u2="0.374" v2="0.124" v1="0.0635" variant="" />
		<Element name="pulque_bottle.tex" u1="0.5635" u2="0.624" v2="0.9365" v1="0.876" variant="" />
		<Element name="rice_spirits_bottle.tex" u1="0.1885" u2="0.249" v2="0.999" v1="0.9385" variant="" />
		<Element name="rice_wine_bottle.tex" u1="0.126" u2="0.1865" v2="0.9365" v1="0.876" variant="" />
		<Element name="ruincacao_cream_liqueur_bottle.tex" u1="0.3105703125" u2="0.3710703125" v2="0.749" v1="0.6885" variant="" />
		<Element name="ruincacao_wine_bottle.tex" u1="0.501" u2="0.5615" v2="0.874" v1="0.8135" variant="" />
		<Element name="ruincha_latte_bottle.tex" u1="0.299828125" u2="0.360328125" v2="0.624" v1="0.5635" variant="" />
		<Element name="ruincolate_smoothie_bottle.tex" u1="0.1885" u2="0.249" v2="0.5615" v1="0.501" variant="" />
		<Element name="ruinxocolatl_bottle.tex" u1="0.8105703125" u2="0.8710703125" v2="0.8115" v1="0.751" variant="" />
		<Element name="rumchata_bottle.tex" u1="0.4385" u2="0.499" v2="0.9365" v1="0.876" variant="" />
		<Element name="seaweed_shake_bottle.tex" u1="0.7480703125" u2="0.786109375" v2="0.749" v1="0.6885" variant="" />
		<Element name="soda_bottle.tex" u1="0.251" u2="0.3085703125" v2="0.0615" v1="0.0039296875" variant="" />
		<Element name="sparklingwine_bottle.tex" u1="0.68459375" u2="0.7421640625" v2="0.499" v1="0.440453125" variant="" />
		<Element name="spoiled_drink_bottle.tex" u1="0.6230703125" u2="0.6835703125" v2="0.4365" v1="0.376" variant="" />
		<Element name="sushibiscus_bottle.tex" u1="0.499046875" u2="0.559546875" v2="0.3115" v1="0.251" variant="" />
		<Element name="sweet_rice_drink_bottle.tex" u1="0.126" u2="0.1865" v2="0.999" v1="0.9385" variant="" />
		<Element name="tea_lumpy_vodka_bottle.tex" u1="0.374046875" u2="0.434546875" v2="0.8115" v1="0.751" variant="" />
		<Element name="tea_ruincolate_latte_bottle.tex" u1="0.3730703125" u2="0.4335703125" v2="0.749" v1="0.6885" variant="" />
		<Element name="tequila_bottle.tex" u1="0.1885" u2="0.249" v2="0.6865" v1="0.626" variant="" />
		<Element name="toffee_latte_bottle.tex" u1="0.251" u2="0.297828125" v2="0.624" v1="0.5644765625" variant="" />
		<Element name="tomato_juice_bottle.tex" u1="0.501" u2="0.5615" v2="0.374" v1="0.3135" variant="" />
		<Element name="veggie_tea_bottle.tex" u1="0.4385" u2="0.497046875" v2="0.3115" v1="0.2519765625" variant="" />
		<Element name="water_clean_bottle.tex" u1="0.876" u2="0.92478125" v2="0.6874765625" v1="0.6269765625" variant="" />
		<Element name="water_clean_ice_bottle.tex" u1="0.376" u2="0.4365" v2="0.249" v1="0.1885" variant="" />
		<Element name="water_dirty_bottle.tex" u1="0.3135" u2="0.374" v2="0.1865" v1="0.126" variant="" />
		<Element name="water_dirty_ice_bottle.tex" u1="0.251" u2="0.3115" v2="0.124" v1="0.0635" variant="" />
		<Element name="water_mineral_bottle.tex" u1="0.626" u2="0.6865" v2="0.6865" v1="0.626" variant="" />
		<Element name="water_salty_bottle.tex" u1="0.1885" u2="0.249" v2="0.0615" v1="0.001" variant="" />
		<Element name="watermelon_juice_bottle.tex" u1="0.3135" u2="0.374" v2="0.5615" v1="0.501" variant="" />
		<Element name="wine_bottle.tex" u1="0.626" u2="0.68259375" v2="0.499" v1="0.4414296875" variant="" />
		<Element name="bucket_clean.tex" u1="0.751" u2="0.809546875" v2="0.563453125" v1="0.50490625" variant="" />
		<Element name="bucket_dirty.tex" u1="0.751" u2="0.809546875" v2="0.624" v1="0.565453125" variant="" />
		<Element name="bucket_empty.tex" u1="0.5635" u2="0.624" v2="0.499" v1="0.4385" variant="" />
		<Element name="bucket_ice.tex" u1="0.9121328125" u2="0.97165625" v2="0.749" v1="0.6894765625" variant="" />
		<Element name="bucket_salty.tex" u1="0.5605703125" u2="0.6210703125" v2="0.4365" v1="0.376" variant="" />
		<Element name="bucket_steel_empty.tex" u1="0.6885" u2="0.749" v2="0.5615" v1="0.501" variant="" />
		<Element name="bucket_woodie_empty.tex" u1="0.8135" u2="0.874" v2="0.6865" v1="0.626" variant="" />
		<Element name="caffeinberry_bean.tex" u1="0.126" u2="0.1865" v2="0.0615" v1="0.001" variant="" />
		<Element name="caffeinberry_bean_cooked.tex" u1="0.4385" u2="0.499" v2="0.374" v1="0.3135" variant="" />
		<Element name="caffeinberry_bush_dug.tex" u1="0.376" u2="0.4365" v2="0.3115" v1="0.251" variant="" />
		<Element name="spice_caffeinpepper.tex" u1="0.3135" u2="0.374" v2="0.249" v1="0.1885" variant="" />
		<Element name="spice_caffeinpepper_over.tex" u1="0.1885" u2="0.249" v2="0.124" v1="0.0635" variant="" />
		<Element name="wx78module_nonedrunk.tex" u1="0.376" u2="0.4355234375" v2="0.9365" v1="0.8769765625" variant="" />
		<Element name="hydration.tex" u1="0.5635" u2="0.624" v2="0.624" v1="0.5635" variant="" />
		<Element name="secretknowledge.tex" u1="0.876" u2="0.9365" v2="0.9365" v1="0.876" variant="" />
		<Element name="absinthe.tex" u1="0.001" u2="0.0615" v2="0.6865" v1="0.626" variant="" />
		<Element name="areuhi.tex" u1="0.2480703125" u2="0.3085703125" v2="0.749" v1="0.6885" variant="" />
		<Element name="banana_juice.tex" u1="0.4980703125" u2="0.5585703125" v2="0.4365" v1="0.376" variant="" />
		<Element name="berries_juice.tex" u1="0.251" u2="0.3115" v2="0.1865" v1="0.126" variant="" />
		<Element name="berry_brandy.tex" u1="0.0635" u2="0.124" v2="0.5615" v1="0.501" variant="" />
		<Element name="berry_gin.tex" u1="0.001" u2="0.0615" v2="0.5615" v1="0.501" variant="" />
		<Element name="blacktea.tex" u1="0.3135" u2="0.374" v2="0.3115" v1="0.251" variant="" />
		<Element name="blacktea_iced.tex" u1="0.251" u2="0.3115" v2="0.249" v1="0.1885" variant="" />
		<Element name="butterbeer.tex" u1="0.501" u2="0.5615" v2="0.5615" v1="0.501" variant="" />
		<Element name="cactus_tea.tex" u1="0.501" u2="0.5615" v2="0.499" v1="0.4385" variant="" />
		<Element name="cactusflower_tea.tex" u1="0.4355703125" u2="0.4960703125" v2="0.4365" v1="0.376" variant="" />
		<Element name="caffeinberry_juice.tex" u1="0.1885" u2="0.249" v2="0.1865" v1="0.126" variant="" />
		<Element name="carrot_tea.tex" u1="0.126" u2="0.1865" v2="0.124" v1="0.0635" variant="" />
		<Element name="cherry_bloom_madhu.tex" u1="0.251" u2="0.3115" v2="0.999" v1="0.9385" variant="" />
		<Element name="cherry_bloom_rum.tex" u1="0.186546875" u2="0.247046875" v2="0.8115" v1="0.751" variant="" />
		<Element name="cherry_doctor_cola.tex" u1="0.3135" u2="0.374" v2="0.999" v1="0.9385" variant="" />
		<Element name="cherry_honey_tea.tex" u1="0.376" u2="0.4365" v2="0.999" v1="0.9385" variant="" />
		<Element name="cherry_roseberries_tea.tex" u1="0.251" u2="0.3115" v2="0.874" v1="0.8135" variant="" />
		<Element name="coconut_juice.tex" u1="0.061546875" u2="0.122046875" v2="0.8115" v1="0.751" variant="" />
		<Element name="cola.tex" u1="0.376" u2="0.4365" v2="0.374" v1="0.3135" variant="" />
		<Element name="colaquantum.tex" u1="0.251" u2="0.3115" v2="0.3115" v1="0.251" variant="" />
		<Element name="corn_beer.tex" u1="0.001" u2="0.0615" v2="0.0615" v1="0.001" variant="" />
		<Element name="corn_whiskey.tex" u1="0.424828125" u2="0.4823984375" v2="0.624" v1="0.5644765625" variant="" />
		<Element name="disinfectant.tex" u1="0.4385" u2="0.499" v2="0.5624765625" v1="0.5019765625" variant="" />
		<Element name="dragonjuice.tex" u1="0.0635" u2="0.124" v2="0.075171875" v1="0.014671875" variant="" />
		<Element name="empty_cup.tex" u1="0.1885" u2="0.249" v2="0.624" v1="0.5635" variant="" />
		<Element name="fig_juice.tex" u1="0.4385" u2="0.499" v2="0.4999765625" v1="0.4394765625" variant="" />
		<Element name="fruitjuice.tex" u1="0.1885" u2="0.249" v2="0.249" v1="0.1885" variant="" />
		<Element name="fruitsoda.tex" u1="0.126" u2="0.1865" v2="0.1865" v1="0.126" variant="" />
		<Element name="fuer.tex" u1="0.3135" u2="0.374" v2="0.374" v1="0.3135" variant="" />
		<Element name="giant_blueberry_gin.tex" u1="0.0635" u2="0.124" v2="0.874" v1="0.8135" variant="" />
		<Element name="giant_blueberry_wine.tex" u1="0.8135" u2="0.874" v2="0.874" v1="0.8135" variant="" />
		<Element name="glowberry_gin.tex" u1="0.126" u2="0.1865" v2="0.6865" v1="0.626" variant="" />
		<Element name="glowberryjuice.tex" u1="0.251" u2="0.3115" v2="0.374" v1="0.3135" variant="" />
		<Element name="glowberrywine.tex" u1="0.001" u2="0.0615" v2="0.124" v1="0.0635" variant="" />
		<Element name="goopydrink.tex" u1="0.0635" u2="0.124" v2="0.137671875" v1="0.077171875" variant="" />
		<Element name="greentea.tex" u1="0.3730703125" u2="0.4335703125" v2="0.4365" v1="0.376" variant="" />
		<Element name="hibiscustea.tex" u1="0.3105703125" u2="0.3710703125" v2="0.4365" v1="0.376" variant="" />
		<Element name="hotruincolate.tex" u1="0.9375234375" u2="0.9980234375" v2="0.999" v1="0.9385" variant="" />
		<Element name="kahlua.tex" u1="0.0635" u2="0.1210703125" v2="0.749" v1="0.690453125" variant="" />
		<Element name="kumis.tex" u1="0.3750234375" u2="0.4355234375" v2="0.499" v1="0.4385" variant="" />
		<Element name="lemonlimesoda.tex" u1="0.1885" u2="0.249" v2="0.3115" v1="0.251" variant="" />
		<Element name="lotustea.tex" u1="0.126" u2="0.1865" v2="0.249" v1="0.1885" variant="" />
		<Element name="lumpy_beer.tex" u1="0.499046875" u2="0.559546875" v2="0.8115" v1="0.751" variant="" />
		<Element name="lumpy_tea.tex" u1="0.4385" u2="0.499" v2="0.6865" v1="0.626" variant="" />
		<Element name="lumpy_vodka.tex" u1="0.1855703125" u2="0.2460703125" v2="0.749" v1="0.6885" variant="" />
		<Element name="lumpy_wine.tex" u1="0.626" u2="0.6865" v2="0.999" v1="0.9385" variant="" />
		<Element name="madhu.tex" u1="0.001" u2="0.0615" v2="0.1865" v1="0.126" variant="" />
		<Element name="mixflower.tex" u1="0.1885" u2="0.249" v2="0.374" v1="0.3135" variant="" />
		<Element name="moon_blossom_tea.tex" u1="0.7480703125" u2="0.8085703125" v2="0.8115" v1="0.751" variant="" />
		<Element name="mulled.tex" u1="0.126" u2="0.1865" v2="0.3115" v1="0.251" variant="" />
		<Element name="noblewine.tex" u1="0.0635" u2="0.124" v2="0.200171875" v1="0.139671875" variant="" />
		<Element name="nut_corn_whiskey.tex" u1="0.311546875" u2="0.372046875" v2="0.8115" v1="0.751" variant="" />
		<Element name="pale_beer.tex" u1="0.0635" u2="0.124" v2="0.999" v1="0.9385" variant="" />
		<Element name="pale_whiskey.tex" u1="0.6855703125" u2="0.7460703125" v2="0.249" v1="0.1885" variant="" />
		<Element name="petals_berry_brandy.tex" u1="0.376" u2="0.4365" v2="0.8749765625" v1="0.8144765625" variant="" />
		<Element name="pineananas_juice.tex" u1="0.0635" u2="0.124" v2="0.9365" v1="0.876" variant="" />
		<Element name="pineananassoda.tex" u1="0.001" u2="0.0615" v2="0.9365" v1="0.876" variant="" />
		<Element name="pomegranate_juice.tex" u1="0.126" u2="0.1865" v2="0.374" v1="0.3135" variant="" />
		<Element name="pulque.tex" u1="0.5635" u2="0.624" v2="0.999" v1="0.9385" variant="" />
		<Element name="rice_spirits.tex" u1="0.001" u2="0.059546875" v2="0.8115" v1="0.752953125" variant="" />
		<Element name="rice_wine.tex" u1="0.001" u2="0.0615" v2="0.874" v1="0.8135" variant="" />
		<Element name="ruincacao_cream_liqueur.tex" u1="0.0635" u2="0.124" v2="0.624" v1="0.5635" variant="" />
		<Element name="ruincacao_wine.tex" u1="0.501" u2="0.5615" v2="0.9365" v1="0.876" variant="" />
		<Element name="ruincha_latte.tex" u1="0.6855703125" u2="0.7460703125" v2="0.749" v1="0.6885" variant="" />
		<Element name="ruincolate_smoothie.tex" u1="0.751" u2="0.8115" v2="0.874" v1="0.8135" variant="" />
		<Element name="ruinxocolatl.tex" u1="0.8135" u2="0.874" v2="0.9365" v1="0.876" variant="" />
		<Element name="rumchata.tex" u1="0.3135" u2="0.374" v2="0.874" v1="0.8135" variant="" />
		<Element name="seaweed_shake.tex" u1="0.501" u2="0.5615" v2="0.624" v1="0.5635" variant="" />
		<Element name="soda.tex" u1="0.0635" u2="0.124" v2="0.262671875" v1="0.202171875" variant="" />
		<Element name="sparklingwine.tex" u1="0.2480703125" u2="0.3085703125" v2="0.4365" v1="0.376" variant="" />
		<Element name="spoiled_drink.tex" u1="0.3125234375" u2="0.3730234375" v2="0.499" v1="0.4385" variant="" />
		<Element name="sushibiscus.tex" u1="0.1855703125" u2="0.2460703125" v2="0.4365" v1="0.376" variant="" />
		<Element name="sweet_rice_drink.tex" u1="0.1885" u2="0.249" v2="0.9365" v1="0.876" variant="" />
		<Element name="tea_lumpy_vodka.tex" u1="0.4385" u2="0.499" v2="0.999" v1="0.9385" variant="" />
		<Element name="tea_ruincolate_latte.tex" u1="0.5635" u2="0.624" v2="0.6865" v1="0.626" variant="" />
		<Element name="tequila.tex" u1="0.0635" u2="0.124" v2="0.6865" v1="0.626" variant="" />
		<Element name="toffee_latte.tex" u1="0.8750234375" u2="0.9355234375" v2="0.999" v1="0.9385" variant="" />
		<Element name="tomato_juice.tex" u1="0.251" u2="0.3105234375" v2="0.499" v1="0.4385" variant="" />
		<Element name="veggie_tea.tex" u1="0.001" u2="0.0615" v2="0.249" v1="0.1885" variant="" />
		<Element name="water_clean.tex" u1="0.9355703125" u2="0.993140625" v2="0.8115" v1="0.7519765625" variant="" />
		<Element name="water_clean_ice.tex" u1="0.126" u2="0.1835703125" v2="0.4365" v1="0.3769765625" variant="" />
		<Element name="water_dirty.tex" u1="0.0635" u2="0.124" v2="0.325171875" v1="0.264671875" variant="" />
		<Element name="water_dirty_ice.tex" u1="0.0635" u2="0.1210703125" v2="0.3866953125" v1="0.327171875" variant="" />
		<Element name="water_mineral.tex" u1="0.6230703125" u2="0.6835703125" v2="0.749" v1="0.6885" variant="" />
		<Element name="water_salty.tex" u1="0.001" u2="0.0615" v2="0.3115" v1="0.251" variant="" />
		<Element name="watermelon_juice.tex" u1="0.362328125" u2="0.422828125" v2="0.624" v1="0.5635" variant="" />
		<Element name="wine.tex" u1="0.1885" u2="0.249" v2="0.499" v1="0.4385" variant="" />
		<Element name="campdesalinator.tex" u1="0.850609375" u2="0.9101328125" v2="0.749" v1="0.6894765625" variant="" />
		<Element name="campkettle.tex" u1="0.126" u2="0.1865" v2="0.499" v1="0.4385" variant="" />
		<Element name="distillers.tex" u1="0.501" u2="0.5615" v2="0.6865" v1="0.626" variant="" />
		<Element name="kettle.tex" u1="0.626" u2="0.6865" v2="0.5615" v1="0.501" variant="" />
		<Element name="portablekettle.tex" u1="0.751" u2="0.8115" v2="0.6865" v1="0.626" variant="" />
		<Element name="portablekettle_item.tex" u1="0.6885" u2="0.749" v2="0.624" v1="0.5635" variant="" />
		<Element name="boillingrecipcard.tex" u1="0.0635" u2="0.124" v2="0.4491953125" v1="0.3886953125" variant="" />
		<Element name="fermentingrecipcard.tex" u1="0.001" u2="0.0615" v2="0.374" v1="0.3135" variant="" />
		<Element name="ruincacao.tex" u1="0.6855703125" u2="0.7460703125" v2="0.8115" v1="0.751" variant="" />
		<Element name="ruincacao_bean.tex" u1="0.8135" u2="0.8730234375" v2="0.999" v1="0.9385" variant="" />
		<Element name="ruincacao_bean_cooked.tex" u1="0.751" u2="0.8115" v2="0.9365" v1="0.876" variant="" />
		<Element name="ruincacao_seed.tex" u1="0.624046875" u2="0.6835703125" v2="0.8115" v1="0.751" variant="" />
		<Element name="ruincacao_tree_dug.tex" u1="0.6885" u2="0.749" v2="0.8749765625" v1="0.8144765625" variant="" />
		<Element name="tea_seed.tex" u1="0.001" u2="0.0615" v2="0.499" v1="0.4385" variant="" />
		<Element name="tea_seed_cooked.tex" u1="0.0635" u2="0.122046875" v2="0.499" v1="0.4511953125" variant="" />
		<Element name="tea_tree_bush_dug.tex" u1="0.001" u2="0.0615" v2="0.4365" v1="0.376" variant="" />
		<Element name="tealeaves.tex" u1="0.874046875" u2="0.934546875" v2="0.5693125" v1="0.5088125" variant="" />
		<Element name="tealeaves_dried.tex" u1="0.936546875" u2="0.997046875" v2="0.625953125" v1="0.565453125" variant="" />
		<Element name="dark_ruincolate.tex" u1="0.5605703125" u2="0.6210703125" v2="0.749" v1="0.6885" variant="" />
		<Element name="ruin_schokakola.tex" u1="0.751" u2="0.8115" v2="0.999" v1="0.9385" variant="" />
		<Element name="ruincolate.tex" u1="0.6885" u2="0.7480234375" v2="0.9365" v1="0.8769765625" variant="" />
		<Element name="white_ruincolate.tex" u1="0.626" u2="0.6865" v2="0.874" v1="0.8135" variant="" />
		<Element name="well.tex" u1="0.936546875" u2="0.997046875" v2="0.563453125" v1="0.502953125" variant="" />
		<Element name="well_burying_kit.tex" u1="0.561546875" u2="0.622046875" v2="0.8115" v1="0.751" variant="" />
		<Element name="well_drilling_item.tex" u1="0.92678125" u2="0.98728125" v2="0.6874765625" v1="0.627953125" variant="" />
		<Element name="well_kit.tex" u1="0.811546875" u2="0.872046875" v2="0.5615" v1="0.501" variant="" />
		<Element name="well_sprinkler_kit.tex" u1="0.874046875" u2="0.934546875" v2="0.624" v1="0.5713125" variant="" />
	</Elements>
</Atlas>